phono3py-3.24.0.dist-info/RECORD
phono3py-3.24.0.dist-info/WHEEL
phono3py-3.24.0.dist-info/entry_points.txt
phono3py-3.24.0.dist-info/METADATA
phono3py-3.24.0.dist-info/licenses/LICENSE
phono3py/_phononcalc.cpython-311-darwin.so
phono3py/version.py
phono3py/api_isotope.py
phono3py/_version.py
phono3py/__init__.py
phono3py/api_phono3py.py
phono3py/_phono3py.cpython-311-darwin.so
phono3py/_recgrid.cpython-311-darwin.so
phono3py/api_jointdos.py
phono3py/file_IO.py
phono3py/interface/fc_calculator.py
phono3py/interface/phono3py_yaml.py
phono3py/interface/wien2k.py
phono3py/interface/calculator.py
phono3py/conductivity/wigner_rta.py
phono3py/conductivity/direct_solution_base.py
phono3py/conductivity/direct_solution.py
phono3py/conductivity/wigner_direct_solution.py
phono3py/conductivity/init_rta.py
phono3py/conductivity/wigner_base.py
phono3py/conductivity/rta.py
phono3py/conductivity/rta_base.py
phono3py/conductivity/utils.py
phono3py/conductivity/init_direct_solution.py
phono3py/conductivity/kubo_rta.py
phono3py/conductivity/kubo_base.py
phono3py/conductivity/base.py
phono3py/other/isotope.py
phono3py/other/kaccum.py
phono3py/other/tetrahedron_method.py
phono3py/phonon/grid.py
phono3py/phonon/solver.py
phono3py/phonon/group_velocity_matrix.py
phono3py/phonon/velocity_operator.py
phono3py/phonon/heat_capacity_matrix.py
phono3py/phonon/func.py
phono3py/phonon3/collision_matrix.py
phono3py/phonon3/triplets.py
phono3py/phonon3/interaction.py
phono3py/phonon3/real_to_reciprocal.py
phono3py/phonon3/gruneisen.py
phono3py/phonon3/joint_dos.py
phono3py/phonon3/fc3.py
phono3py/phonon3/real_self_energy.py
phono3py/phonon3/reciprocal_to_normal.py
phono3py/phonon3/dataset.py
phono3py/phonon3/displacement_fc3.py
phono3py/phonon3/imag_self_energy.py
phono3py/phonon3/spectral_function.py
phono3py/scripts/phono3py_coleigplot.py
phono3py/scripts/phono3py_kdeplot.py
phono3py/scripts/phono3py_load.py
phono3py/scripts/phono3py.py
phono3py/scripts/phono3py_kaccum.py
phono3py/cui/triplets_info.py
phono3py/cui/kaccum_script.py
phono3py/cui/create_force_constants.py
phono3py/cui/create_force_sets.py
