Metadata-Version: 2.4
Name: phono3py
Version: 3.24.0
Summary: This is the phono3py module.
Author-Email: Atsushi Togo <atztogo@gmail.com>
License-Expression: BSD-3-Clause
License-File: LICENSE
Project-URL: Homepage, https://phonopy.github.io/phono3py/
Project-URL: Repository, https://github.com/phonopy/phono3py
Requires-Python: >=3.10
Requires-Dist: numpy
Requires-Dist: scipy
Requires-Dist: PyYAML
Requires-Dist: matplotlib
Requires-Dist: h5py
Requires-Dist: spglib>=2.5.0
Requires-Dist: phonopy<2.48,>=2.47.0
